dubstub/__init__.py
dubstub/format.py
dubstub/fs.py
dubstub/py.typed
dubstub/source.py
dubstub/toml.py
dubstub/util.py
dubstub/cli/__init__.py
dubstub/cli/common.py
dubstub/cli/main.py
dubstub/config/__init__.py
dubstub/config/gen_docs.py
dubstub/config/main.py
dubstub/config/match_ctx.py
dubstub/config/pattern.py
dubstub/config/show.py
dubstub/diff/__init__.py
dubstub/diff/impl.py
dubstub/diff/main.py
dubstub/evaluate/__init__.py
dubstub/evaluate/gen_dubstub.py
dubstub/evaluate/gen_mypy.py
dubstub/evaluate/gen_pyright.py
dubstub/evaluate/main.py
dubstub/generate/__init__.py
dubstub/generate/fs.py
dubstub/generate/main.py
dubstub/generate/stubber.py
dubstub-1.4.1.dist-info/entry_points.txt
dubstub-1.4.1.dist-info/licenses/LICENSE
dubstub-1.4.1.dist-info/WHEEL
dubstub-1.4.1.dist-info/METADATA
dubstub-1.4.1.dist-info/RECORD
