Metadata-Version: 2.4
Name: dubstub
Version: 1.4.1
Summary: A simple "dumb" python type stub generator
Keywords: PEP,stubs,type,stubgen,484
Requires-Python: >=3.10
Classifier: Intended Audience :: Developers
Classifier: License :: OSI Approved :: MIT License
Classifier: Programming Language :: Python :: 3 :: Only
Classifier: Programming Language :: Python :: 3.10
Classifier: Programming Language :: Python :: 3.11
Classifier: Programming Language :: Python :: 3.12
Classifier: Programming Language :: Python :: 3.13
License-File: LICENSE
Requires-Dist: tomli==2.*; python_version < '3.11'
Requires-Dist: tomli-w==1.*
Requires-Dist: black==25.* ; extra == "def-fmt"
Requires-Dist: isort==6.* ; extra == "def-fmt"
Requires-Dist: black==25.* ; extra == "dev"
Requires-Dist: isort==6.* ; extra == "dev"
Requires-Dist: pyright==1.1.* ; extra == "dev"
Requires-Dist: pylint==3.* ; extra == "dev"
Requires-Dist: pytest==8.* ; extra == "dev"
Requires-Dist: pycmarkgfm==1.* ; extra == "dev"
Requires-Dist: uv==0.6.* ; extra == "dev"
Requires-Dist: rich==14.* ; extra == "eval"
Requires-Dist: pyright==1.1.* ; extra == "eval"
Requires-Dist: mypy==1.15.* ; extra == "eval"
Project-URL: Changelog, https://github.com/Kimundi/dubstub/blob/main/CHANGELOG.md
Project-URL: Documentation, https://github.com/Kimundi/dubstub/blob/main/README.md
Project-URL: Homepage, https://github.com/Kimundi/dubstub
Project-URL: Repository, https://github.com/Kimundi/dubstub
Provides-Extra: def-fmt
Provides-Extra: dev
Provides-Extra: eval
